{
	"_type": "export",
	"__export_format": 3,
	"__export_date": "2019-02-07T10:21:18.078Z",
	"__export_source": "insomnia.desktop.app:v6.3.2",
	"resources": [
		{
			"_id": "wrk_c48f7e408af149fc8f06096a892361e2",
			"created": 1549355857571,
			"description": "",
			"modified": 1549355857571,
			"name": "ProjectCarTravel",
			"parentId": null,
			"_type": "workspace"
		},
		{
			"_id": "env_61e1a58e93fc420aa26099e905df489b",
			"color": null,
			"created": 1549355857798,
			"data": {},
			"isPrivate": false,
			"metaSortKey": 1549355857798,
			"modified": 1549355857798,
			"name": "New Environment",
			"parentId": "wrk_c48f7e408af149fc8f06096a892361e2",
			"_type": "environment"
		},
		{
			"_id": "jar_d7d36b45c1a2423f9a235dbfeadfe05b",
			"cookies": [],
			"created": 1549355857816,
			"modified": 1549355857816,
			"name": "Default Jar",
			"parentId": "wrk_c48f7e408af149fc8f06096a892361e2",
			"_type": "cookie_jar"
		},
		{
			"_id": "fld_ad005e28d8bd4dd7b1835306f94864d5",
			"created": 1549355887309,
			"description": "",
			"environment": {},
			"metaSortKey": -1549355887309,
			"modified": 1549355887309,
			"name": "Users",
			"parentId": "wrk_c48f7e408af149fc8f06096a892361e2",
			"_type": "request_group"
		},
		{
			"_id": "fld_3c51dd43da0040c09c1e41fb4f59da19",
			"created": 1549358937914,
			"description": "",
			"environment": {},
			"metaSortKey": -1549358937914,
			"modified": 1549358937914,
			"name": "Clients",
			"parentId": "wrk_c48f7e408af149fc8f06096a892361e2",
			"_type": "request_group"
		},
		{
			"_id": "fld_c90d8d3dd6e84cfc91a757124eafdf9d",
			"created": 1549457474239,
			"description": "",
			"environment": {},
			"metaSortKey": -1549457474239,
			"modified": 1549457474239,
			"name": "Agents",
			"parentId": "wrk_c48f7e408af149fc8f06096a892361e2",
			"_type": "request_group"
		},
		{
			"_id": "fld_89de97fb3ea743cd90e6ec7fcdc66d32",
			"created": 1549466608283,
			"description": "",
			"environment": {},
			"metaSortKey": -1549466608283,
			"modified": 1549466608283,
			"name": "Authentification",
			"parentId": "wrk_c48f7e408af149fc8f06096a892361e2",
			"_type": "request_group"
		},
		{
			"_id": "req_c63c5d19bfae46faa3bd86676c016bcd",
			"authentication": {},
			"body": {},
			"created": 1549355894579,
			"description": "",
			"headers": [],
			"isPrivate": false,
			"metaSortKey": -1549355894579,
			"method": "GET",
			"modified": 1549531922748,
			"name": "List users",
			"parameters": [],
			"parentId": "fld_ad005e28d8bd4dd7b1835306f94864d5",
			"settingDisableRenderRequestBody": false,
			"settingEncodeUrl": true,
			"settingMaxTimelineDataSize": 1000,
			"settingRebuildPath": true,
			"settingSendCookies": true,
			"settingStoreCookies": true,
			"url": "http://localhost:8001/api/v1/user",
			"_type": "request"
		},
		{
			"_id": "req_386325bb136142baba558a70510d885d",
			"authentication": {},
			"body": {
				"mimeType": "application/json",
				"text": "{\n\t\"email\" : \"test3@test.com\",\n\t\"refId\" : \"5c5957bcf281d28230dd2232\",\n\t\"role\" : \"Client\"\n}"
			},
			"created": 1549356152623,
			"description": "",
			"headers": [
				{
					"id": "pair_2f7306ed40324687bffad4200dc456c5",
					"name": "Content-Type",
					"value": "application/json"
				}
			],
			"isPrivate": false,
			"metaSortKey": -1549356152623,
			"method": "POST",
			"modified": 1549458278556,
			"name": "Create user",
			"parameters": [],
			"parentId": "fld_ad005e28d8bd4dd7b1835306f94864d5",
			"settingDisableRenderRequestBody": false,
			"settingEncodeUrl": true,
			"settingMaxTimelineDataSize": 1000,
			"settingRebuildPath": true,
			"settingSendCookies": true,
			"settingStoreCookies": true,
			"url": "http://localhost:8001/api/v1/user",
			"_type": "request"
		},
		{
			"_id": "req_c0c12f26874e4cb19e2aaa06e694c3c1",
			"authentication": {},
			"body": {},
			"created": 1549358388544,
			"description": "",
			"headers": [],
			"isPrivate": false,
			"metaSortKey": -1549358388544,
			"method": "GET",
			"modified": 1549529941844,
			"name": "Get user",
			"parameters": [],
			"parentId": "fld_ad005e28d8bd4dd7b1835306f94864d5",
			"settingDisableRenderRequestBody": false,
			"settingEncodeUrl": true,
			"settingMaxTimelineDataSize": 1000,
			"settingRebuildPath": true,
			"settingSendCookies": true,
			"settingStoreCookies": true,
			"url": "http://localhost:8001/api/v1/user/5c5aff2d7fff5431024cc33b",
			"_type": "request"
		},
		{
			"_id": "req_2fe76c6d436d4fa4a36b281ae22332f7",
			"authentication": {},
			"body": {},
			"created": 1549457502580,
			"description": "",
			"headers": [],
			"isPrivate": false,
			"metaSortKey": -1549457502580,
			"method": "DELETE",
			"modified": 1549467350564,
			"name": "Remove user",
			"parameters": [],
			"parentId": "fld_ad005e28d8bd4dd7b1835306f94864d5",
			"settingDisableRenderRequestBody": false,
			"settingEncodeUrl": true,
			"settingMaxTimelineDataSize": 1000,
			"settingRebuildPath": true,
			"settingSendCookies": true,
			"settingStoreCookies": true,
			"url": "http://localhost:8001/api/v1/user/5c5adc60bc1cd1e28d7fab14",
			"_type": "request"
		},
		{
			"_id": "req_10880bba59c44d88a1c376520d5fd852",
			"authentication": {},
			"body": {
				"mimeType": "application/json",
				"text": "{\n\t\"email\" : \"1234@info.com\"\n}"
			},
			"created": 1549458114938,
			"description": "",
			"headers": [
				{
					"id": "pair_c1604a78b12542f6831f0dce6023f4ec",
					"name": "Content-Type",
					"value": "application/json"
				}
			],
			"isPrivate": false,
			"metaSortKey": -1549458114938,
			"method": "PATCH",
			"modified": 1549534593442,
			"name": "Update user",
			"parameters": [],
			"parentId": "fld_ad005e28d8bd4dd7b1835306f94864d5",
			"settingDisableRenderRequestBody": false,
			"settingEncodeUrl": true,
			"settingMaxTimelineDataSize": 1000,
			"settingRebuildPath": true,
			"settingSendCookies": true,
			"settingStoreCookies": true,
			"url": "http://localhost:8001/api/v1/user/5c5aff6d7fff5431024cc33d",
			"_type": "request"
		},
		{
			"_id": "req_764db5a6d79549d3b011c2250eab6e41",
			"authentication": {},
			"body": {
				"mimeType": "application/json",
				"text": "{\n\t\"firstname\" : \"guillaume\",\n\t\"lastname\" : \"leblanc\",\n\t\"email\" : \"leblanc@test.com\",\n\t\"phoneNumber\" : \"123456789\",\n\t\"address\" : {\n\t\t\"street\" : \"rue de la citadelle\",\n\t\t\"number\" : \"112\",\n\t\t\"zip\" : \"7500\",\n\t\t\"city\" : \"Tournai\",\n\t\t\"country\" : \"Belgique\"\n\t},\n\t\"companyName\" : \"Tululu\",\n\t\"tvaNumber\" : \"1234567890\",\n\t\"iban\" : \"BE68539007547034\"\n}"
			},
			"created": 1549358950777,
			"description": "",
			"headers": [
				{
					"id": "pair_978470f6ff4e44d796e94f79a36c23d6",
					"name": "Content-Type",
					"value": "application/json"
				}
			],
			"isPrivate": false,
			"metaSortKey": -1549358950777,
			"method": "POST",
			"modified": 1549444097385,
			"name": "Create client",
			"parameters": [],
			"parentId": "fld_3c51dd43da0040c09c1e41fb4f59da19",
			"settingDisableRenderRequestBody": false,
			"settingEncodeUrl": true,
			"settingMaxTimelineDataSize": 1000,
			"settingRebuildPath": true,
			"settingSendCookies": true,
			"settingStoreCookies": true,
			"url": "http://localhost:8001/api/v1/client",
			"_type": "request"
		},
		{
			"_id": "req_35d03222c1d94d80b250c760f79aa417",
			"authentication": {},
			"body": {},
			"created": 1549441013202,
			"description": "",
			"headers": [],
			"isPrivate": false,
			"metaSortKey": -1549441013202,
			"method": "GET",
			"modified": 1549441023012,
			"name": "List clients",
			"parameters": [],
			"parentId": "fld_3c51dd43da0040c09c1e41fb4f59da19",
			"settingDisableRenderRequestBody": false,
			"settingEncodeUrl": true,
			"settingMaxTimelineDataSize": 1000,
			"settingRebuildPath": true,
			"settingSendCookies": true,
			"settingStoreCookies": true,
			"url": "http://localhost:8001/api/v1/client",
			"_type": "request"
		},
		{
			"_id": "req_6cacd061bfb74902906940f56c142997",
			"authentication": {},
			"body": {},
			"created": 1549441255868,
			"description": "",
			"headers": [],
			"isPrivate": false,
			"metaSortKey": -1549441255868,
			"method": "GET",
			"modified": 1549441845990,
			"name": "Get client",
			"parameters": [],
			"parentId": "fld_3c51dd43da0040c09c1e41fb4f59da19",
			"settingDisableRenderRequestBody": false,
			"settingEncodeUrl": true,
			"settingMaxTimelineDataSize": 1000,
			"settingRebuildPath": true,
			"settingSendCookies": true,
			"settingStoreCookies": true,
			"url": "http://localhost:8001/api/v1/client/5c59a71a7d067db12f9eff05",
			"_type": "request"
		},
		{
			"_id": "req_1c1079aa05b64639a71cd3dfc03a8587",
			"authentication": {},
			"body": {},
			"created": 1549441707625,
			"description": "",
			"headers": [],
			"isPrivate": false,
			"metaSortKey": -1549441707625,
			"method": "DELETE",
			"modified": 1549441851198,
			"name": "Remove client",
			"parameters": [],
			"parentId": "fld_3c51dd43da0040c09c1e41fb4f59da19",
			"settingDisableRenderRequestBody": false,
			"settingEncodeUrl": true,
			"settingMaxTimelineDataSize": 1000,
			"settingRebuildPath": true,
			"settingSendCookies": true,
			"settingStoreCookies": true,
			"url": "http://localhost:8001/api/v1/client/5c59a71a7d067db12f9eff05",
			"_type": "request"
		},
		{
			"_id": "req_7f02e019684d483c94bc66b1abadabed",
			"authentication": {},
			"body": {},
			"created": 1549457551071,
			"description": "",
			"headers": [],
			"isPrivate": false,
			"metaSortKey": -1549457551071,
			"method": "GET",
			"modified": 1549457640235,
			"name": "List agents",
			"parameters": [],
			"parentId": "fld_c90d8d3dd6e84cfc91a757124eafdf9d",
			"settingDisableRenderRequestBody": false,
			"settingEncodeUrl": true,
			"settingMaxTimelineDataSize": 1000,
			"settingRebuildPath": true,
			"settingSendCookies": true,
			"settingStoreCookies": true,
			"url": "http://localhost:8001/api/v1/agent",
			"_type": "request"
		},
		{
			"_id": "req_35951f9bea6b479ebe76475f275d0984",
			"authentication": {},
			"body": {
				"mimeType": "application/json",
				"text": "{\n\t\"firstname\" : \"david\",\n\t\"lastname\" : \"magnée\",\n\t\"email\" : \"david@magnee.com\"\n}"
			},
			"created": 1549457568904,
			"description": "",
			"headers": [
				{
					"id": "pair_998f6221899d4358aaba08ccf7524cc4",
					"name": "Content-Type",
					"value": "application/json"
				}
			],
			"isPrivate": false,
			"metaSortKey": -1549457568904,
			"method": "POST",
			"modified": 1549458521907,
			"name": "Create agent",
			"parameters": [],
			"parentId": "fld_c90d8d3dd6e84cfc91a757124eafdf9d",
			"settingDisableRenderRequestBody": false,
			"settingEncodeUrl": true,
			"settingMaxTimelineDataSize": 1000,
			"settingRebuildPath": true,
			"settingSendCookies": true,
			"settingStoreCookies": true,
			"url": "http://localhost:8001/api/v1/agent",
			"_type": "request"
		},
		{
			"_id": "req_90e55aac4d12453d84932d99bdf1016f",
			"authentication": {},
			"body": {},
			"created": 1549457607067,
			"description": "",
			"headers": [],
			"isPrivate": false,
			"metaSortKey": -1549457607067,
			"method": "GET",
			"modified": 1549457665221,
			"name": "Get agent",
			"parameters": [],
			"parentId": "fld_c90d8d3dd6e84cfc91a757124eafdf9d",
			"settingDisableRenderRequestBody": false,
			"settingEncodeUrl": true,
			"settingMaxTimelineDataSize": 1000,
			"settingRebuildPath": true,
			"settingSendCookies": true,
			"settingStoreCookies": true,
			"url": "http://localhost:8001/api/v1/agent/",
			"_type": "request"
		},
		{
			"_id": "req_99a90070bb17411382504255ce2d0f02",
			"authentication": {},
			"body": {},
			"created": 1549457690856,
			"description": "",
			"headers": [],
			"isPrivate": false,
			"metaSortKey": -1549457690856,
			"method": "DELETE",
			"modified": 1549458489771,
			"name": "Remove agent",
			"parameters": [],
			"parentId": "fld_c90d8d3dd6e84cfc91a757124eafdf9d",
			"settingDisableRenderRequestBody": false,
			"settingEncodeUrl": true,
			"settingMaxTimelineDataSize": 1000,
			"settingRebuildPath": true,
			"settingSendCookies": true,
			"settingStoreCookies": true,
			"url": "http://localhost:8001/api/v1/agent/5c5adb534e45fde177b67570",
			"_type": "request"
		},
		{
			"_id": "req_8c2592d052e34ffc8e6b38ce37a8eff5",
			"authentication": {},
			"body": {
				"mimeType": "application/json",
				"text": "{\n\t\"email\" : \"leblanc@test.com\",\n\t\"password\" : \"NrciyTsuT52Z\"\n}"
			},
			"created": 1549466659741,
			"description": "",
			"headers": [
				{
					"id": "pair_62af1a0fe848451dbb550f88bca67750",
					"name": "Content-Type",
					"value": "application/json"
				}
			],
			"isPrivate": false,
			"metaSortKey": -1549466659741,
			"method": "POST",
			"modified": 1549467534633,
			"name": "Login",
			"parameters": [],
			"parentId": "fld_89de97fb3ea743cd90e6ec7fcdc66d32",
			"settingDisableRenderRequestBody": false,
			"settingEncodeUrl": true,
			"settingMaxTimelineDataSize": 1000,
			"settingRebuildPath": true,
			"settingSendCookies": true,
			"settingStoreCookies": true,
			"url": "http://localhost:8001/api/v1/auth/login",
			"_type": "request"
		}
	]
}